timefrequency/__init__.py
timefrequency-0.0.0.dev0.dist-info/LICENSE
timefrequency-0.0.0.dev0.dist-info/METADATA
timefrequency-0.0.0.dev0.dist-info/WHEEL
timefrequency-0.0.0.dev0.dist-info/entry_points.txt
timefrequency-0.0.0.dev0.dist-info/top_level.txt
timefrequency-0.0.0.dev0.dist-info/RECORD
