Metadata-Version: 2.1
Name: timefrequency
Version: 0.0.0.dev0
Summary: timefrequency
Home-page: https://github.com/larsrollik/timefrequency
Author: Lars B. Rollik
Author-email: L.B.Rollik@protonmail.com
License: BSD 3-Clause License        
Platform: UNKNOWN
Requires-Python: >=3.6
License-File: LICENSE
Provides-Extra: dev
Requires-Dist: black ; extra == 'dev'
Requires-Dist: pytest-cov ; extra == 'dev'
Requires-Dist: pytest ; extra == 'dev'
Requires-Dist: gitpython ; extra == 'dev'
Requires-Dist: coverage (>=5.0.3) ; extra == 'dev'
Requires-Dist: bump2version ; extra == 'dev'
Requires-Dist: pre-commit ; extra == 'dev'
Requires-Dist: flake8 ; extra == 'dev'
